handlers/__init__.py
keyboards/__init__.py
middlewares/__init__.py
splaueef/__init__.py
splaueef/advanced_keyboards.py
splaueef/analytics.py
splaueef/api_helpers.py
splaueef/bot.py
splaueef/bot_config.py
splaueef/cache.py
splaueef/command_helpers.py
splaueef/commands.py
splaueef/db_helpers.py
splaueef/error_handling.py
splaueef/file_helpers.py
splaueef/handlers.py
splaueef/image_processing.py
splaueef/keyboards.py
splaueef/localization.py
splaueef/menu_helpers.py
splaueef/middlewares.py
splaueef/response_templates.py
splaueef/state_helpers.py
splaueef/states.py
splaueef/templates.py
splaueef/test_helpers.py
splaueef/tools.py
splaueef/user_management.py
splaueef/utils.py
states/__init__.py
tests/__init__.py
tests/test_bot.py
tests/test_core.py
tests/test_keyboards.py
tests/test_middlewares.py
tests/test_utils.py
splaueef-0.1.10.dist-info/METADATA
splaueef-0.1.10.dist-info/WHEEL
splaueef-0.1.10.dist-info/entry_points.txt
splaueef-0.1.10.dist-info/top_level.txt
splaueef-0.1.10.dist-info/RECORD
