Metadata-Version: 2.2
Name: splaueef
Version: 0.1.10
Summary: Helper library for working with aiogram, including tools for creating keyboards, handling commands, image processing, and database management.
Home-page: https://github.com/Splaueef/aiohelp.git
Author: Splaueef
Author-email: Splaueef@gmail.com
Classifier: Programming Language :: Python :: 3
Classifier: License :: OSI Approved :: MIT License
Classifier: Operating System :: OS Independent
Requires-Python: >=3.8
Requires-Dist: aiogram>=3.0
Requires-Dist: certifi
Requires-Dist: pyzbar
Requires-Dist: pytesseract
Requires-Dist: pillow
Requires-Dist: aiosqlite
Dynamic: author
Dynamic: author-email
Dynamic: classifier
Dynamic: description
Dynamic: description-content-type
Dynamic: home-page
Dynamic: requires-dist
Dynamic: requires-python
Dynamic: summary
